manim_live
