Metadata-Version: 1.1
Name: manim-live
Version: 0.0.9
Summary: Program that uses manim and can display animations and be controlled live
Home-page: UNKNOWN
Author: Cory Alexander Balaton
Author-email: cory.balaton@gmail.com
License: MIT
Keywords: animations
Platform: UNKNOWN
Classifier: Development Status :: 2 - Pre-Alpha
Classifier: Intended Audience :: Education
Classifier: Operating System :: MacOS :: MacOS X
Classifier: License :: OSI Approved :: MIT License
Classifier: Programming Language :: Python :: 3
